MANIFEST.in
requirements.txt
setup.cfg
setup.py
djangotransifex/__init__.py
djangotransifex/api.py
djangotransifex/app_settings.py
djangotransifex/exceptions.py
djangotransifex/models.py
djangotransifex/version.txt
djangotransifex/views.py
djangotransifex.egg-info/PKG-INFO
djangotransifex.egg-info/SOURCES.txt
djangotransifex.egg-info/dependency_links.txt
djangotransifex.egg-info/not-zip-safe
djangotransifex.egg-info/requires.txt
djangotransifex.egg-info/top_level.txt
djangotransifex/management/__init__.py
djangotransifex/management/commands/__init__.py
djangotransifex/management/commands/tx.py
test_project/__init__.py
test_project/manage.py
test_project/settings.py
test_project/urls.py
tests/__init__.py
tests/conftest.py
tests/test_api.py