Metadata-Version: 1.1
Name: djangotransifex
Version: 0.1.10
Summary: A Django api to Transifex
Home-page: https://github.com/jakul/django-transifex
Author: Craig Blaszczyk
Author-email: masterjakul@gmail.com
License: BSD
Platform: UNKNOWN
Classifier: Environment :: Web Environment
Classifier: Framework :: Django
Classifier: Intended Audience :: Developers
Classifier: License :: OSI Approved :: BSD License
Classifier: Operating System :: OS Independent
Classifier: Programming Language :: Python
Classifier: Topic :: Software Development :: Libraries :: Python Modules
